sdl_bgi/__init__.py
sdl_bgi/sdl_bgi.py
sdl_bgi-3.0.4.dist-info/METADATA
sdl_bgi-3.0.4.dist-info/WHEEL
sdl_bgi-3.0.4.dist-info/licenses/LICENSE
sdl_bgi-3.0.4.dist-info/RECORD
