Metadata-Version: 2.4
Name: sdl_bgi
Version: 3.0.4
Summary: SDL-based 'GRAPHICS.H' implementation
Project-URL: Homepage, https://sdl-bgi.sourceforge.io/
Author-email: "Guido Gonzato, PhD" <guido.gonzato@gmail.com>
License: // ZLib License
License-File: LICENSE
Keywords: BGI,GRAPHICS.H,SDL
Classifier: Intended Audience :: Developers
Classifier: Intended Audience :: Education
Classifier: License :: OSI Approved :: zlib/libpng License
Classifier: Operating System :: OS Independent
Classifier: Programming Language :: Python :: 3
Classifier: Topic :: Software Development :: Libraries :: Python Modules
Requires-Python: >=3.8
